MANIFEST.in
README.md
requirements.txt
setup.py
acellera_htmd.egg-info/PKG-INFO
acellera_htmd.egg-info/SOURCES.txt
acellera_htmd.egg-info/dependency_links.txt
acellera_htmd.egg-info/entry_points.txt
acellera_htmd.egg-info/not-zip-safe
acellera_htmd.egg-info/requires.txt
acellera_htmd.egg-info/top_level.txt
htmd/__init__.py
htmd/config.py
htmd/decorators.py
htmd/dock.py
htmd/home.py
htmd/kinetics.py
htmd/kineticshmm.py
htmd/latest.py
htmd/logging.ini
htmd/metricdata.py
htmd/model.py
htmd/modelhmm.py
htmd/mutualinformation.py
htmd/numbautil.py
htmd/parallelprogress.py
htmd/pathplanning.py
htmd/session.py
htmd/simlist.py
htmd/ui.py
htmd/units.py
htmd/util.py
htmd/version.py
htmd/versionwarnings.py
htmd/adaptive/__init__.py
htmd/adaptive/adaptive.py
htmd/adaptive/adaptivebandit.py
htmd/adaptive/adaptivegoal.py
htmd/adaptive/adaptivegoaleg.py
htmd/adaptive/adaptiverun.py
htmd/adaptive/util.py
htmd/apps/__init__.py
htmd/apps/acemd.py
htmd/apps/pmemd.py
htmd/builder/__init__.py
htmd/builder/amber.py
htmd/builder/builder.py
htmd/builder/charmm.py
htmd/builder/ionize.py
htmd/builder/loopmodeler.py
htmd/builder/preparation.py
htmd/builder/solvate.py
htmd/clustering/__init__.py
htmd/clustering/kcenters.py
htmd/clustering/regular.py
htmd/mdengine/__init__.py
htmd/mdengine/acemd/__init__.py
htmd/mdengine/acemd/acemd.py
htmd/membranebuilder/__init__.py
htmd/membranebuilder/build_membrane.py
htmd/membranebuilder/globalminimization.py
htmd/membranebuilder/ljfluid.py
htmd/membranebuilder/pdbreporter.py
htmd/membranebuilder/ringpenetration.py
htmd/membranebuilder/simulate_openmm.py
htmd/molecule/__init__.py
htmd/molecule/molecule.py
htmd/molecule/util.py
htmd/projections/__init__.py
htmd/projections/gwpca.py
htmd/projections/kmeanstri.py
htmd/projections/metric.py
htmd/projections/metriccoordinate.py
htmd/projections/metricdihedral.py
htmd/projections/metricdistance.py
htmd/projections/metricfluctuation.py
htmd/projections/metricplumed2.py
htmd/projections/metricrmsd.py
htmd/projections/metricsasa.py
htmd/projections/metricsecondarystructure.py
htmd/projections/metricshell.py
htmd/projections/metricsphericalcoordinate.py
htmd/projections/metrictmscore.py
htmd/projections/tica.py
htmd/protocols/__init__.py
