Metadata-Version: 1.2
Name: acellera-htmd
Version: 1.23.6
Summary: High throughput molecular dynamics (HTMD)
Home-page: https://www.htmd.org
Maintainer: Acellera Ltd
Maintainer-email: info@acellera.com
License: UNKNOWN
Platform: UNKNOWN
